{
  "name": "Dra. Elva Clementina Guerrero Abarca",
  "specialty": "Ginecólogo",
  "rating": 5,
  "reviewCount": 5,
  "photoUrl": "https://pixel-p3.s3.us-east-1.amazonaws.com/doctor/avatar/a5fea4fe/a5fea4fe-6c45-4ba0-a94d-5de632d44a09_140_square.jpg",
  "about": "",
  "addresses": [
    {
      "full": "EJE 5 SUR 206,"
    },
    {
      "full": "Ejercito Nacional No. 613, Col. Granada,"
    },
    {
      "full": "EJE 5 SUR 206,"
    },
    {
      "full": "Ejercito Nacional No. 613, Col. Granada,"
    }
  ],
  "services": [
    {
      "name": "Primera visita Ginecología y Obstetricia",
      "price": ""
    }
  ],
  "insurance": [
    "Aseguradoras"
  ],
  "education": [],
  "languages": [],
  "profileUrl": "https://www.doctoralia.com.mx/elva-clementina-guerrero-abarca-2/ginecologo/ciudad-de-mexico#address-id=327645&is-online-only=false&filters%5Bspecializations%5D%5B%5D=30",
  "scrapedAt": "2026-01-22T02:08:11.621Z",
  "localPhotoPath": "doctors_data/ginecologo/miguel-hidalgo/dra__elva_clementina_guerrero_abarca.webp"
}