{
  "name": "Carlos Guillerm Maquita Nakano",
  "specialty": "Ginecólogo",
  "rating": null,
  "reviewCount": 0,
  "photoUrl": "//platform.docplanner.com/img/general/doctor/doctor-default-80-80.png?1981952613",
  "about": "",
  "addresses": [
    {
      "full": "Mollendo 664, Lindavista,"
    },
    {
      "full": "Mollendo 664, Lindavista,"
    }
  ],
  "services": [],
  "insurance": [
    "Aseguradoras"
  ],
  "education": [],
  "languages": [],
  "profileUrl": "https://www.doctoralia.com.mx/carlos-guillerm-maquita-nakano/ginecologo/gustavo-a-madero#address-id=111854&is-online-only=false&filters%5Bspecializations%5D%5B%5D=30",
  "scrapedAt": "2026-01-21T03:09:54.387Z",
  "localPhotoPath": null
}