{
  "name": "Dr. Radames Rivas López",
  "specialty": "Ginecólogo",
  "rating": 5,
  "reviewCount": 12,
  "photoUrl": "//platform.docplanner.com/img/general/doctor/doctor-default-80-80.png?1981952613",
  "about": "",
  "addresses": [
    {
      "full": "Camino sta Teresa 1055,"
    },
    {
      "full": "Camino sta Teresa 1055,"
    }
  ],
  "services": [
    {
      "name": "Primera visita Ginecología y Obstetricia",
      "price": ""
    }
  ],
  "insurance": [
    "Aseguradoras"
  ],
  "education": [],
  "languages": [],
  "profileUrl": "https://www.doctoralia.com.mx/radames-rivas-lopez/ginecologo/magdalena-contreras#address-id=39815&is-online-only=false&filters%5Bspecializations%5D%5B%5D=30",
  "scrapedAt": "2026-01-21T02:58:10.453Z",
  "localPhotoPath": null
}