{
  "name": "Gilberto Saenz Pascacio",
  "specialty": "Ginecólogo",
  "rating": null,
  "reviewCount": 0,
  "photoUrl": "//platform.docplanner.com/img/general/doctor/doctor-default-80-80.png?1981952613",
  "about": "",
  "addresses": [
    {
      "full": "Bogota no. 706, Lindavista,"
    },
    {
      "full": "Bogota no. 706, Lindavista,"
    }
  ],
  "services": [],
  "insurance": [
    "Aseguradoras"
  ],
  "education": [],
  "languages": [],
  "profileUrl": "https://www.doctoralia.com.mx/gilberto-saenz-pascacio/ginecologo/gustavo-a-madero#address-id=110376&is-online-only=false&filters%5Bspecializations%5D%5B%5D=30",
  "scrapedAt": "2026-01-21T03:17:45.765Z",
  "localPhotoPath": null
}