{
  "name": "Mario Roberto Rodríguez Bosch",
  "specialty": "Ginecólogo",
  "rating": 5,
  "reviewCount": 1,
  "photoUrl": "//platform.docplanner.com/img/general/doctor/doctor-default-80-80.png?1981952613",
  "about": "",
  "addresses": [
    {
      "full": "Homero 1804 - 503 - A,"
    },
    {
      "full": "Homero 1804 - 503 - A,"
    }
  ],
  "services": [],
  "insurance": [
    "Aseguradoras"
  ],
  "education": [],
  "languages": [],
  "profileUrl": "https://www.doctoralia.com.mx/mario-roberto-rodriguez-bosch/ginecologo/miguel-hidalgo#address-id=109271&is-online-only=false&filters%5Bspecializations%5D%5B%5D=30",
  "scrapedAt": "2026-01-21T03:07:49.181Z",
  "localPhotoPath": null
}