{
  "name": "Dra. Maria Del Rocio Barajas Riebeling",
  "specialty": "Ginecólogo",
  "rating": 5,
  "reviewCount": 5,
  "photoUrl": "https://pixel-p3.s3.us-east-1.amazonaws.com/doctor/avatar/3831a8a8/3831a8a8-8c73-4cbd-b550-1ad5cb9cc143_140_square.jpg",
  "about": "",
  "addresses": [
    {
      "full": "Av De Los Maestros 2016,"
    },
    {
      "full": "De los Maestros 2016,"
    },
    {
      "full": "Av De Los Maestros 2016,"
    },
    {
      "full": "De los Maestros 2016,"
    }
  ],
  "services": [],
  "insurance": [
    "Aseguradoras"
  ],
  "education": [],
  "languages": [],
  "profileUrl": "https://www.doctoralia.com.mx/maria-del-rocio-barajas-riebeling/ginecologo/guadalajara#address-id=64563&is-online-only=false&filters%5Bspecializations%5D%5B%5D=30",
  "scrapedAt": "2026-01-22T04:21:42.684Z",
  "localPhotoPath": "doctors_data/ginecologo/zapopan/dra__maria_del_rocio_barajas_riebeling.webp"
}