{
  "name": "Dr. Piel De Angel Espósitos Peniche",
  "specialty": "Ginecólogo",
  "rating": 1,
  "reviewCount": 3,
  "photoUrl": "https://s3.us-east-1.amazonaws.com/doctoralia.com.mx/doctor/fb2cf6/fb2cf6af61faad9e0f1e1a6a48d8b5b5_140_square.jpg",
  "about": "",
  "addresses": [
    {
      "full": "Calle 26 #199 X 17 Y 7 Fracc Altabrisa,"
    },
    {
      "full": "Calle 26 #199 X 17 Y 7 Fracc Altabrisa,"
    }
  ],
  "services": [],
  "insurance": [
    "Aseguradoras"
  ],
  "education": [],
  "languages": [],
  "profileUrl": "https://www.doctoralia.com.mx/piel-de-angel-espositos-peniche/ginecologo/merida#address-id=148106&is-online-only=false&filters%5Bspecializations%5D%5B%5D=30",
  "scrapedAt": "2026-01-22T01:44:29.046Z",
  "localPhotoPath": "doctors_data/ginecologo/merida/dr__piel_de_angel_esp_sitos_peniche.webp"
}