{
  "name": "Dr. Ibarra Sergio Minakata",
  "specialty": "Ginecólogo",
  "rating": 5,
  "reviewCount": 2,
  "photoUrl": "//platform.docplanner.com/img/general/doctor/doctor-default-80-80.png?1981952613",
  "about": "",
  "addresses": [
    {
      "full": "Justo Sierra 2135,"
    },
    {
      "full": "Justo Sierra 2135,"
    }
  ],
  "services": [],
  "insurance": [
    "Aseguradoras"
  ],
  "education": [],
  "languages": [],
  "profileUrl": "https://www.doctoralia.com.mx/ibarra-sergio-minakata/ginecologo/guadalajara#address-id=46858&is-online-only=false&filters%5Bspecializations%5D%5B%5D=30",
  "scrapedAt": "2026-01-21T03:32:04.289Z",
  "localPhotoPath": null
}