{
  "name": "Dra. Hortencia Barba Ruiz",
  "specialty": "Ginecólogo",
  "rating": null,
  "reviewCount": 0,
  "photoUrl": "//platform.docplanner.com/img/general/doctor/doctor-default-80-80.png?1981952613",
  "about": "",
  "addresses": [
    {
      "full": "Circ. Alvarez Del Castillo,"
    },
    {
      "full": "Gral Eulogio Parra 2796,"
    },
    {
      "full": "jose maria heredia 2960,"
    },
    {
      "full": "Circ. Alvarez Del Castillo,"
    },
    {
      "full": "Gral Eulogio Parra 2796,"
    },
    {
      "full": "jose maria heredia 2960,"
    }
  ],
  "services": [
    {
      "name": "Consulta de primera vez",
      "price": "• Desde $1,000"
    },
    {
      "name": "Consulta en línea",
      "price": "• Desde $1,000"
    },
    {
      "name": "Consulta subsecuente",
      "price": "• Desde $1,000"
    },
    {
      "name": "Primera visita Ginecología y Obstetricia",
      "price": ""
    },
    {
      "name": "Visita Ginecología y Obstetricia",
      "price": ""
    }
  ],
  "insurance": [
    "Aseguradoras"
  ],
  "education": [],
  "languages": [],
  "profileUrl": "https://www.doctoralia.com.mx/hortencia-barba-ruiz/ginecologo/guadalajara#address-id=220685&is-online-only=false&filters%5Bspecializations%5D%5B%5D=30",
  "scrapedAt": "2026-01-21T03:30:35.540Z",
  "localPhotoPath": null
}