{
  "name": "Dra. Brenda Elizabeth Barragan Ruiz",
  "specialty": "Ginecólogo",
  "rating": null,
  "reviewCount": 0,
  "photoUrl": "//platform.docplanner.com/img/general/doctor/doctor-default-80-80.png?1981952613",
  "about": "",
  "addresses": [
    {
      "full": "Av.Cruz Del Sur No.2612-102,"
    },
    {
      "full": "Calz. Lázaro Cárdenas 2063,"
    },
    {
      "full": "Isla Antillas 2220,"
    },
    {
      "full": "Av.Cruz Del Sur No.2612-102,"
    },
    {
      "full": "Calz. Lázaro Cárdenas 2063,"
    },
    {
      "full": "Isla Antillas 2220,"
    }
  ],
  "services": [],
  "insurance": [
    "Aseguradoras"
  ],
  "education": [],
  "languages": [],
  "profileUrl": "https://www.doctoralia.com.mx/brenda-elizabeth-barragan-ruiz/ginecologo/guadalajara#address-id=241944&is-online-only=false&filters%5Bspecializations%5D%5B%5D=30",
  "scrapedAt": "2026-01-21T03:31:00.574Z",
  "localPhotoPath": null
}