{
  "name": "Dr. José Ruíz Medina",
  "specialty": "Ginecólogo",
  "rating": 5,
  "reviewCount": 1,
  "photoUrl": "https://s3.us-east-1.amazonaws.com/doctoralia.com.mx/doctor/0d214e/0d214e476ead8a4c9b067eaa65110070_140_square.jpg",
  "about": "",
  "addresses": [
    {
      "full": "Hospital san angel inn universidad av churubusco # 601 col xoco 8 piso consultorio 821 ,"
    },
    {
      "full": "Hospital san angel inn universidad av churubusco # 601 col xoco 8 piso consultorio 821 ,"
    }
  ],
  "services": [
    {
      "name": "Primera visita Ginecología y Obstetricia",
      "price": ""
    },
    {
      "name": "Cesárea",
      "price": ""
    },
    {
      "name": "Colposcopia",
      "price": ""
    },
    {
      "name": "Histerectomía",
      "price": ""
    },
    {
      "name": "Ultrasonido obstétrico",
      "price": ""
    }
  ],
  "insurance": [
    "Aseguradoras"
  ],
  "education": [],
  "languages": [],
  "profileUrl": "https://www.doctoralia.com.mx/jose-ruiz-medina/ginecologo/benito-juarez#address-id=77508&is-online-only=false&filters%5Bspecializations%5D%5B%5D=30",
  "scrapedAt": "2026-01-22T03:09:47.825Z",
  "localPhotoPath": "doctors_data/ginecologo/benito-juarez/dr__jos__ru_z_medina.webp"
}